{
    "key": "ui_options_page_68741220841e1",
    "title": "Blog Single",
    "active": true,
    "menu_order": 0,
    "page_title": "Blog Single",
    "menu_slug": "blog-single",
    "parent_slug": "theme-options",
    "advanced_configuration": 0,
    "icon_url": "",
    "menu_title": "",
    "position": "",
    "redirect": false,
    "description": "",
    "menu_icon": [],
    "update_button": "Update",
    "updated_message": "Options Updated",
    "capability": "edit_posts",
    "data_storage": "options",
    "post_id": "",
    "autoload": 0,
    "_parent": 79,
    "modified": 1752437342
}
